vmdrs_py-0.3.0.dist-info/METADATA
vmdrs_py-0.3.0.dist-info/WHEEL
vmdrs_py-0.3.0.dist-info/license_files/LICENSE.md
vmdrs_py-0.3.0.dist-info/license_files/LICENSE-APACHE-2.0
vmdrs_py-0.3.0.dist-info/license_files/LICENSE-ISS
vmdrs_py-0.3.0.dist-info/license_files/LICENSE-MIT
vmdrs_py/__init__.py
vmdrs_py/vmdrs_py.cpython-311-darwin.so
vmdrs_py-0.3.0.dist-info/RECORD
