Metadata-Version: 2.1
Name: vmdrs-py
Version: 0.3.0
Classifier: Programming Language :: Rust
Classifier: Programming Language :: Python :: Implementation :: CPython
Classifier: Programming Language :: Python :: Implementation :: PyPy
Requires-Dist: numpy >=1.20
License-File: LICENSE.md
License-File: LICENSE-APACHE-2.0
License-File: LICENSE-ISS
License-File: LICENSE-MIT
Summary: Better, drop in replacement of vmdpy
Keywords: signal-processing,vmd,signal-analysis,python
Author: jiafuei
Requires-Python: >=3.7
Project-URL: Source Code, https://github.com/jiafuei/vmdrs-py
